{
  "$schema": "./node_modules/nx/schemas/workspace-schema.json",
  "version": 2,
  "projects": {
    "groupware": "apps/groupware",
    "groupware-components": "libs/groupware/components",
    "groupware-e2e": "apps/groupware-e2e",
    "groupware-types": "libs/groupware/types",
    "personal": "apps/personal",
    "personal-components": "libs/personal/components",
    "personal-config": "libs/personal/config",
    "personal-constants": "libs/personal/constants",
    "personal-contexts": "libs/personal/contexts",
    "personal-e2e": "apps/personal-e2e",
    "personal-hooks": "libs/personal/hooks",
    "personal-lib": "libs/personal/lib",
    "personal-templates": "libs/personal/templates",
    "personal-utils": "libs/personal/utils"
  }
}
